{
  "project_info": {
    "project_number": "69289952300",
    "firebase_url": "https://flutterfootball.firebaseio.com",
    "project_id": "flutterfootball",
    "storage_bucket": "flutterfootball.appspot.com"
  },
  "client": [
    {
      "client_info": {
        "mobilesdk_app_id": "1:69289952300:android:122a492c519a86ac80bd89",
        "android_client_info": {
          "package_name": "com.rasp.flutterfootball"
        }
      },
      "oauth_client": [
        {
          "client_id": "69289952300-e554r33hjnom6oomoome0ogal47vt1ag.apps.googleusercontent.com",
          "client_type": 3
        }
      ],
      "api_key": [
        {
          "current_key": "AIzaSyD2pSBU3wTvo-nPc5aKDtKXT9BlhT63rFA"
        }
      ],
      "services": {
        "appinvite_service": {
          "other_platform_oauth_client": [
            {
              "client_id": "69289952300-e554r33hjnom6oomoome0ogal47vt1ag.apps.googleusercontent.com",
              "client_type": 3
            }
          ]
        }
      },
      "admob_app_id": "ca-app-pub-4679672544714691~4802759913"
    }
  ],
  "configuration_version": "1"
}